xshell/__init__.py
xshell/xshell.py
xshell-1.4.1.dist-info/LICENSE
xshell-1.4.1.dist-info/METADATA
xshell-1.4.1.dist-info/WHEEL
xshell-1.4.1.dist-info/top_level.txt
xshell-1.4.1.dist-info/RECORD
