Metadata-Version: 2.1
Name: xshell
Version: 1.4.1
Summary: Run `xshell.embed()`, you can do anything, in the Interactive Console.
Home-page: https://github.com/neoctobers/xshell
Author: @neoctobers
Author-email: neoctobers@gmail.com
License: UNKNOWN
Platform: UNKNOWN
Classifier: Programming Language :: Python :: 3
Classifier: License :: OSI Approved :: MIT License
Classifier: Operating System :: OS Independent
